reddist/__init__.py
reddist/cachers/__init__.py
reddist/cachers/base.py
reddist/cachers/memory.py
reddist/cachers/pickle.py
reddist/cachers/redis.py
reddist/utils/__init__.py
reddist/utils/sorting.py
reddist/utils/submission.py
reddist-0.1.2.dist-info/WHEEL
reddist-0.1.2.dist-info/METADATA
reddist-0.1.2.dist-info/RECORD
