Metadata-Version: 2.1
Name: reddist
Version: 0.1.2
Summary: Just a simple library for caching reddit posts
License: MIT
Author: CaffieneDuck
Author-email: samrid.pandit@gmail.com
Requires-Python: >=3.9,<3.11
Classifier: License :: OSI Approved :: MIT License
Classifier: Programming Language :: Python :: 3
Classifier: Programming Language :: Python :: 3.10
Classifier: Programming Language :: Python :: 3.9
Requires-Dist: aiofiles (==0.6.0)
Requires-Dist: aioredis (>=2.0.1,<3.0.0)
Requires-Dist: asyncpraw (>=7.5.0,<8.0.0)
